Metadata-Version: 2.1
Name: transactions-analysis-sk1
Version: 0.1.0
Summary: Пакет для анализа финансовых транзакций
Author-email: Stanislav Kuleshov <phtschmth171@gmail.com>
Requires-Dist: pandas
